EASYFORMER/__init__.py
EASYFORMER/encoders.py
EASYFORMER/transformers.py
easyformer-0.1.0.dist-info/LICENSE
easyformer-0.1.0.dist-info/METADATA
easyformer-0.1.0.dist-info/WHEEL
easyformer-0.1.0.dist-info/top_level.txt
easyformer-0.1.0.dist-info/RECORD
