Metadata-Version: 2.1
Name: easyformer
Version: 0.1.0
Summary: A package for encoding and scaling data for ML pipelines
Home-page: https://github.com/gaharivatsa/easyformer
Author: Harivatsa G A
Author-email: gaharivatsa@gmail.com
Classifier: Programming Language :: Python :: 3
Classifier: License :: OSI Approved :: MIT License
Classifier: Operating System :: OS Independent
Requires-Python: >=3.6
License-File: LICENSE
Requires-Dist: scikit-learn
Requires-Dist: pandas
Requires-Dist: numpy
